LICENSE
MANIFEST.in
README.md
setup.py
src/_uncalled4.cpython-38-x86_64-linux-gnu.so
src/cpp/.util.hpp.swp
src/cpp/aln.hpp
src/cpp/config.cpp
src/cpp/config.hpp
src/cpp/dtw.cpp
src/cpp/dtw.hpp
src/cpp/event_detector.cpp
src/cpp/event_detector.hpp
src/cpp/eventalign.hpp
src/cpp/intervals.cpp
src/cpp/intervals.hpp
src/cpp/normalizer.cpp
src/cpp/normalizer.hpp
src/cpp/pore_model.cpp
src/cpp/pore_model.hpp
src/cpp/pybinder.cpp
src/cpp/read_buffer.cpp
src/cpp/read_buffer.hpp
src/cpp/seq.hpp
src/cpp/signal_processor.hpp
src/cpp/toplevel_prms.hpp
src/cpp/util.cpp
src/cpp/util.hpp
src/uncalled4/__about__.py
src/uncalled4/__init__.py
src/uncalled4/__main__.py
src/uncalled4/align.py
src/uncalled4/argparse.py
src/uncalled4/config.py
src/uncalled4/moves.py
src/uncalled4/params.py
src/uncalled4/pore_model.py
src/uncalled4/read_index.py
src/uncalled4/ref_index.py
src/uncalled4/signal_processor.py
src/uncalled4/tracks.py
src/uncalled4/train.py
src/uncalled4.egg-info/PKG-INFO
src/uncalled4.egg-info/SOURCES.txt
src/uncalled4.egg-info/dependency_links.txt
src/uncalled4.egg-info/entry_points.txt
src/uncalled4.egg-info/requires.txt
src/uncalled4.egg-info/top_level.txt
src/uncalled4/__pycache__/__about__.cpython-38.pyc
src/uncalled4/__pycache__/__init__.cpython-38.pyc
src/uncalled4/__pycache__/__main__.cpython-38.pyc
src/uncalled4/__pycache__/align.cpython-38.pyc
src/uncalled4/__pycache__/aln.cpython-38.pyc
src/uncalled4/__pycache__/aln_track.cpython-38.pyc
src/uncalled4/__pycache__/argparse.cpython-38.pyc
src/uncalled4/__pycache__/config.cpython-38.pyc
src/uncalled4/__pycache__/dtw.cpython-38.pyc
src/uncalled4/__pycache__/index.cpython-38.pyc
src/uncalled4/__pycache__/layers.cpython-38.pyc
src/uncalled4/__pycache__/moves.cpython-38.pyc
src/uncalled4/__pycache__/params.cpython-38.pyc
src/uncalled4/__pycache__/pore_model.cpython-38.pyc
src/uncalled4/__pycache__/read_index.cpython-38.pyc
src/uncalled4/__pycache__/ref_index.cpython-38.pyc
src/uncalled4/__pycache__/signal_processor.cpython-38.pyc
src/uncalled4/__pycache__/tracks.cpython-38.pyc
src/uncalled4/__pycache__/train.cpython-38.pyc
src/uncalled4/io/__init__.py
src/uncalled4/io/bam.py
src/uncalled4/io/eventalign.py
src/uncalled4/io/m6anet.py
