Metadata-Version: 2.1
Name: uncalled4
Version: 4.1.0
Summary: A toolkit for nanopore signal alignment, analysis, and visualization
Home-page: https://github.com/skovaka/uncalled4
Author: Sam Kovaka
Author-email: skovaka@gmail.com
Classifier: Programming Language :: Python :: 3
Requires-Python: >=3.8
License-File: LICENSE
Requires-Dist: pybind11>=2.6.0
Requires-Dist: pandas>=1.1.5
Requires-Dist: plotly>=5.0.0
Requires-Dist: dash>=2.0.0
Requires-Dist: scipy>=1.5.4
Requires-Dist: toml>=0.10.2
Requires-Dist: ont_fast5_api
Requires-Dist: pysam
Requires-Dist: pyslow5
Requires-Dist: pod5
Requires-Dist: tblib
